js2pysecrets/__init__.py
js2pysecrets/__main__.py
js2pysecrets/base.py
js2pysecrets/cli.py
js2pysecrets/decorators.py
js2pysecrets/node.py
js2pysecrets/settings.py
js2pysecrets/wrapper.py
js2pysecrets-0.1.1.dist-info/LICENSE
js2pysecrets-0.1.1.dist-info/METADATA
js2pysecrets-0.1.1.dist-info/WHEEL
js2pysecrets-0.1.1.dist-info/entry_points.txt
js2pysecrets-0.1.1.dist-info/top_level.txt
js2pysecrets-0.1.1.dist-info/RECORD
