Metadata-Version: 2.1
Name: js2pysecrets
Version: 0.1.1
Summary: Shamir's Secret Sharing - A port of secrets.js-grempe to Python, allowing cross-platform compatible shares between JavaScript and Python.
Home-page: https://github.com/poing/JS2PySecrets/
Author: Brian LaVallee
Author-email: brian.lavallee@invite-comm.jp
Project-URL: Documentation, https://poing.github.io/JS2PySecrets
Project-URL: Source, https://github.com/poing/JS2PySecrets
Project-URL: Bug Tracker, https://github.com/poing/JS2PySecrets/issues/
Keywords: Adi,Adi Shamir,how to share a secret,scheme,secret,secrets.js,secrets,Shamir Secret Sharing Scheme,Shamir's Secret Sharing,Shamir's,Shamir,share,shares,sharing,sss,ssss
Classifier: Development Status :: 4 - Beta
Classifier: Intended Audience :: Developers
Classifier: Intended Audience :: Information Technology
Classifier: Intended Audience :: Other Audience
Classifier: Intended Audience :: System Administrators
Classifier: Intended Audience :: Telecommunications Industry
Classifier: License :: OSI Approved :: MIT License
Classifier: Programming Language :: Python :: 3.11
Classifier: Topic :: Security :: Cryptography
Classifier: Topic :: Security
Classifier: Topic :: Utilities
Classifier: Operating System :: OS Independent
Classifier: Natural Language :: English
Requires-Python: >=3.11
License-File: LICENSE
Provides-Extra: test
Requires-Dist: pytest; extra == "test"
Requires-Dist: coverage; extra == "test"
Requires-Dist: flake8; extra == "test"
Requires-Dist: black; extra == "test"
Requires-Dist: isort; extra == "test"
Requires-Dist: pytest-cov; extra == "test"
Requires-Dist: mypy; extra == "test"
Requires-Dist: gitchangelog; extra == "test"
Requires-Dist: mkdocs; extra == "test"
Requires-Dist: mkdocs-material; extra == "test"
Requires-Dist: faker; extra == "test"
Requires-Dist: pymdown-extensions; extra == "test"
